touchbase/__init__.py
touchbase/helpers.py
touchbase-0.0.1.dist-info/LICENSE
touchbase-0.0.1.dist-info/METADATA
touchbase-0.0.1.dist-info/WHEEL
touchbase-0.0.1.dist-info/top_level.txt
touchbase-0.0.1.dist-info/RECORD
