Metadata-Version: 2.1
Name: touchbase
Version: 0.0.1
Summary: A bundle of functions to connect to Touchbase
Home-page: https://github.com/pypa/sampleproject
Author: Terry Crapts
Author-email: tcrapts@gmail.com
License: UNKNOWN
Platform: UNKNOWN
Classifier: Programming Language :: Python :: 3
Classifier: License :: OSI Approved :: MIT License
Classifier: Operating System :: OS Independent
Requires-Python: >=3.6
